syne_sql_extension/__init__.py
syne_sql_extension/client.py
syne_sql_extension/config.py
syne_sql_extension/exceptions.py
syne_sql_extension/magic.py
syne_sql_extension/py.typed
syne_sql_extension/types.py
syne_sql_extension/utils.py
syne_sql_extension/__pycache__/__init__.cpython-312.opt-1.pyc
syne_sql_extension/__pycache__/__init__.cpython-312.pyc
syne_sql_extension/__pycache__/client.cpython-312.opt-1.pyc
syne_sql_extension/__pycache__/client.cpython-312.pyc
syne_sql_extension/__pycache__/config.cpython-312.opt-1.pyc
syne_sql_extension/__pycache__/config.cpython-312.pyc
syne_sql_extension/__pycache__/exceptions.cpython-312.opt-1.pyc
syne_sql_extension/__pycache__/exceptions.cpython-312.pyc
syne_sql_extension/__pycache__/magic.cpython-312.opt-1.pyc
syne_sql_extension/__pycache__/magic.cpython-312.pyc
syne_sql_extension/__pycache__/types.cpython-312.opt-1.pyc
syne_sql_extension/__pycache__/types.cpython-312.pyc
syne_sql_extension/__pycache__/utils.cpython-312.opt-1.pyc
syne_sql_extension/__pycache__/utils.cpython-312.pyc
syne_sql_extension/config/syne_sql_extension.json
syne_sql_extension/static/extension.css
syne_sql_extension/static/extension.js
syne_sql_extension-1.0.9.data/data/etc/jupyter/jupyter_notebook_config.d/syne_sql_extension.json
syne_sql_extension-1.0.9.data/data/share/jupyter/nbextensions/syne_sql_extension/extension.css
syne_sql_extension-1.0.9.data/data/share/jupyter/nbextensions/syne_sql_extension/extension.js
syne_sql_extension-1.0.9.dist-info/METADATA
syne_sql_extension-1.0.9.dist-info/WHEEL
syne_sql_extension-1.0.9.dist-info/entry_points.txt
syne_sql_extension-1.0.9.dist-info/top_level.txt
syne_sql_extension-1.0.9.dist-info/RECORD
